lazy_import/__init__.py
lazy_import/lazy_import.py
lazy_import/py.typed
lz_import-0.1.2.dist-info/METADATA
lz_import-0.1.2.dist-info/WHEEL
lz_import-0.1.2.dist-info/RECORD
