Metadata-Version: 2.1
Name: lz-import
Version: 0.1.2
Summary: 
Home-page: https://github.com/Ja-sonYun/lazy_import
License: MIT
Keywords: import,lazy,circular
Author: Ja-sonYun
Author-email: killa30867@gmail.com
Requires-Python: >=3.9,<3.12
Classifier: License :: OSI Approved :: MIT License
Classifier: Programming Language :: Python :: 3
Classifier: Programming Language :: Python :: 3.9
Classifier: Programming Language :: Python :: 3.10
Classifier: Programming Language :: Python :: 3.11
Project-URL: Repository, https://github.com/Ja-sonYun/lazy_import
